{
  "title": "प्रार्थी",
  "darshanabhilashiLabel": "दर्शनाभिलाषि",
  "parentsLines": [
    "टेक नारायण सुबेदी ( बुवा)",
    "गीता कुमारी शर्मा (आमा)",
    "अस्मी सुबेदी ( बहिनी )",
    "एवम समस्त सुबेदी परिवार",
    "कुश्मा–०८,पर्वत"
  ],
  "sections": [
    {
      "label": "बुवा / आमाहरू",
      "names": [
        "श्रीमान / श्रीमती नीलकण्ठ सुबेदी / विष्णुमती सुबेदी",
        "श्रीमान / श्रीमती कृष्णप्रसाद सुबेदी / शान्ता सुबेदी",
        "श्रीमान / श्रीमती दिवाकर सुबेदी / पार्वती सुबेदी",
        "श्रीमती राधिका सुबेदी",
        "श्रीमान / श्रीमती राजु सुबेदी / दुर्गा सुबेदी"
      ]
    },
    {
      "label": "फुपू / पुसजुहरु",
      "caption": "स्वागतपेक्षी",
      "names": [
        "सीता देवी पाध्या",
        "गङ्गा देवी पाध्या",
        "श्रीमान / श्रीमती मनोहरी पाध्या / रेवति पाध्यानी",
        "श्रीमान / श्रीमती ईमनाथ गौतम / विष्णुकुमारी गौतम"
      ]
    },
    {
      "label": "दिदी / भिनाजु / बहिनी / ज्वाइँहरू",
      "names": [
        "श्रीमान / श्रीमती जया अर्याल / रमेश अर्याल",
        "श्रीमान / श्रीमती प्रमिला पौडेल / गोविन्दप्रसाद पौडेल",
        "श्रीमान / श्रीमती राधा पौडेल / रामकृष्ण पौडेल",
        "श्रीमान / श्रीमती शर्मिला शर्मा / सन्तोष शर्मा",
        "श्रीमान / श्रीमती सबिना आचार्य / राजन आचार्य",
        "श्रीमान / श्रीमती सुस्मिता अर्याल / जगदीश अर्याल"
      ]
    },
    {
      "label": "दाइ / भाउजू / भाइहरू",
      "names": [
        "श्रीमान / श्रीमती नेत्र सुबेदी / अम्बिका सुबेदी",
        "श्रीमान / श्रीमती दिनेश सुबेदी / पूजा सुबेदी",
        "राजन सुबेदी",
        "मुक्ति सुबेदी",
        "राजीव सुबेदी",
        "सुदीप सुबेदी",
        "मिलन सुबेदी"
      ]
    },
    {
      "label": "भतिज / भतिजी",
      "names": [
        "अंकित सुबेदी",
        "अमन सुबेदी",
        "प्रसिद्ध सुबेदी",
        "प्रसिद्धि सुबेदी"
      ]
    },
    {
      "label": "मावली तर्फ",
      "decoratedLabel": true,
      "names": [
        "विष्णुमती उपाध्यायनी · हजुरआमा",
        "श्रीमान / श्रीमती बालकृष्ण पौडेल / देवी पौडेल ( मामा / माइजू )"
      ]
    }
  ]
}
